odoo/addons/product_compute_template_field_from_variant_helper/README.rst
odoo/addons/product_compute_template_field_from_variant_helper/__init__.py
odoo/addons/product_compute_template_field_from_variant_helper/__manifest__.py
odoo/addons/product_compute_template_field_from_variant_helper/i18n/product_compute_template_field_from_variant_helper.pot
odoo/addons/product_compute_template_field_from_variant_helper/models/__init__.py
odoo/addons/product_compute_template_field_from_variant_helper/models/product_template.py
odoo/addons/product_compute_template_field_from_variant_helper/readme/CONTRIBUTORS.rst
odoo/addons/product_compute_template_field_from_variant_helper/readme/DESCRIPTION.rst
odoo/addons/product_compute_template_field_from_variant_helper/readme/DEVELOP.rst
odoo/addons/product_compute_template_field_from_variant_helper/readme/ROADMAP.rst
odoo/addons/product_compute_template_field_from_variant_helper/static/description/icon.png
odoo/addons/product_compute_template_field_from_variant_helper/static/description/index.html
odoo_addon_product_compute_template_field_from_variant_helper-16.0.1.0.0.2.dist-info/METADATA
odoo_addon_product_compute_template_field_from_variant_helper-16.0.1.0.0.2.dist-info/WHEEL
odoo_addon_product_compute_template_field_from_variant_helper-16.0.1.0.0.2.dist-info/top_level.txt
odoo_addon_product_compute_template_field_from_variant_helper-16.0.1.0.0.2.dist-info/RECORD
