Metadata-Version: 2.1
Name: odoo-addon-product_compute_template_field_from_variant_helper
Version: 16.0.1.0.0.2
Summary: Add technical helper to compute easily template fields from product variant fields
Home-page: https://github.com/OCA/product-attribute
Author: Odoo SA,GRAP,Odoo Community Association (OCA)
Author-email: support@odoo-community.org
License: LGPL-3
Classifier: Programming Language :: Python
Classifier: Framework :: Odoo
Classifier: Framework :: Odoo :: 16.0
Classifier: License :: OSI Approved :: GNU Lesser General Public License v3 (LGPLv3)
Requires-Python: >=3.10
Requires-Dist: odoo<16.1dev,>=16.0a
